resdb_orm/__init__.py
resdb_orm/orm.py
resdb_orm-1.1.5.dist-info/LICENSE
resdb_orm-1.1.5.dist-info/METADATA
resdb_orm-1.1.5.dist-info/WHEEL
resdb_orm-1.1.5.dist-info/top_level.txt
resdb_orm-1.1.5.dist-info/RECORD
