Metadata-Version: 2.1
Name: resdb-orm
Version: 1.1.5
Summary: A simple ORM for ResilientDB's key-value store.
Home-page: https://github.com/ResilientEcosystem/ResDB-ORM
Author: Gopal Nambiar
Author-email: gnambiar@ucdavis.com
License: UNKNOWN
Platform: UNKNOWN
Classifier: Programming Language :: Python :: 3
Classifier: License :: OSI Approved :: Apache Software License
Classifier: Operating System :: OS Independent
Requires-Python: >=3.6
Requires-Dist: requests>=2.32.3
Requires-Dist: PyYAML>=6.0.2
